pytransdec/__init__.py
pytransdec/communication.py
pytransdec/definitions.py
pytransdec/rpi_comm.py
PyTransdec-0.2.1.dist-info/LICENSE
PyTransdec-0.2.1.dist-info/METADATA
PyTransdec-0.2.1.dist-info/WHEEL
PyTransdec-0.2.1.dist-info/top_level.txt
PyTransdec-0.2.1.dist-info/RECORD
