Metadata-Version: 2.1
Name: PyTransdec
Version: 0.2.1
Summary: Transdec environment https://github.com/pwrdc/TransdecEnvironment controlling with Python
Home-page: https://github.com/pwrdc/PyTransdec
Author: Piotr Zielinski
Author-email: piotr_zielinski@g.pl
License: UNKNOWN
Platform: UNKNOWN
Classifier: Programming Language :: Python :: 3
Classifier: License :: OSI Approved :: MIT License
Classifier: Operating System :: OS Independent
Requires-Dist: numpy
Requires-Dist: pandas
Requires-Dist: tqdm
Requires-Dist: opencv-python
Requires-Dist: mlagents (==0.7.0)
